{"assets":{"AED5676E4B539516B44C1FB8D1E3858F":{"type":"texture","index":1,"url":{"native":"assets\/6128F5A6-BB42-4E20-816D-7567EDDC8BB3.pdf"},"width":3888,"height":2592},"45E1395873AAC4F7B3CE3849968C4655":{"type":"texture","index":0,"url":{"native":"assets\/6128F5A6-BB42-4E20-816D-7567EDDC8BB3.pdf"},"width":3888,"height":2592}},"events":[{"effects":[{"beginTime":0,"baseLayer":{"animations":[],"initialState":{"affineTransform":[1,0,0,1,0,0],"masksToBounds":false,"rotation":0,"scale":1,"position":{"pointX":1944,"pointY":1296},"width":3888,"sublayerTransform":[1,0,0,0,0,1,0,0,0,0,1,0,0,0,0,1],"contentsRect":{"y":0,"x":0,"width":1,"height":1},"opacity":1,"edgeAntialiasingMask":251658240,"height":2592,"hidden":false,"anchorPoint":{"pointX":0.5,"pointY":0.5}},"objectID":"0","layers":[{"animations":[],"initialState":{"affineTransform":[1,0,0,1,0,0],"masksToBounds":false,"rotation":0,"scale":1,"position":{"pointX":1944,"pointY":1296},"width":3888,"sublayerTransform":[1,0,0,0,0,1,0,0,0,0,1,-0.00014586630194489994,0,0,0,1],"contentsRect":{"y":0,"x":0,"width":1,"height":1},"opacity":1,"edgeAntialiasingMask":251658240,"height":2592,"hidden":false,"anchorPoint":{"pointX":0.5,"pointY":0.5}},"layers":[{"animations":[],"layers":[],"texturedRectangle":{"isBackgroundTexture":false,"singleTextureOpacity":1,"textureType":0,"textBaseline":0,"textXHeight":0,"isVerticalText":false},"initialState":{"affineTransform":[1,0,0,1,0,0],"masksToBounds":false,"rotation":0,"scale":1,"position":{"pointX":1944,"pointY":1296},"width":3888,"sublayerTransform":[1,0,0,0,0,1,0,0,0,0,1,0,0,0,0,1],"contentsRect":{"y":0,"x":0,"width":1,"height":1},"opacity":1,"edgeAntialiasingMask":0,"height":2592,"hidden":false,"anchorPoint":{"pointX":0.5,"pointY":0.5}},"texture":"AED5676E4B539516B44C1FB8D1E3858F"},{"animations":[{"additive":false,"timeOffset":0,"beginTime":0,"from":{"scalar":false},"repeatCount":0,"fillMode":"both","duration":0.001,"autoreverses":false,"property":"hidden","to":{"scalar":true},"removedOnCompletion":false}],"layers":[],"texturedRectangle":{"isBackgroundTexture":false,"singleTextureOpacity":1,"textureType":0,"textBaseline":0,"textXHeight":0,"isVerticalText":false},"initialState":{"affineTransform":[1,0,0,1,0,0],"masksToBounds":false,"rotation":0,"scale":1,"position":{"pointX":1944,"pointY":1296},"width":3888,"sublayerTransform":[1,0,0,0,0,1,0,0,0,0,1,0,0,0,0,1],"contentsRect":{"y":0,"x":0,"width":1,"height":1},"opacity":1,"edgeAntialiasingMask":0,"height":2592,"hidden":false,"anchorPoint":{"pointX":0.5,"pointY":0.5}},"texture":"45E1395873AAC4F7B3CE3849968C4655"}]}]},"effects":[],"duration":0.001,"type":"transition","attributes":{"direction":0},"name":"none","objectID":"0"}],"automaticPlay":false,"hyperlinks":[],"accessibility":[{"text":"Milad Afshari*","targetRectangle":{"y":2214.3453612327576,"x":1744.5371336936951,"width":442.9541015625,"height":81}},{"text":"wand8.png","targetRectangle":{"y":1428.3582763671875,"x":345.96270751953125,"width":233.70513916015625,"height":233.70513916015625}},{"text":"*Equal Contribution","targetRectangle":{"y":2501.5387206077576,"x":1722.4258055686951,"width":519.5341796875,"height":72}},{"text":"Obliviator Reveals the Cost of Nonlinear Guardedness in Concept Erasure","targetRectangle":{"y":1596.8800296783447,"x":461.08032201044261,"width":3012.7277372851968,"height":113}},{"text":"Ramin Akbari*","targetRectangle":{"y":2214.3453612327576,"x":1045.3116698265076,"width":452.71875,"height":81}},{"text":"Vishnu Naresh Boddeti","targetRectangle":{"y":2214.3453612327576,"x":2395.2442870140076,"width":698.8330078125,"height":81}},{"text":"final.png","targetRectangle":{"y":88.008598327636719,"x":1239.048583984375,"width":1454.9310302734375,"height":1457.9310302734375}},{"text":"cropped-milad-afshari (2).jpg","targetRectangle":{"y":1810.2261206871738,"x":1796.5922467476596,"width":339.82029082710847,"height":339.82805633545263}},{"text":"ramin_akbari.JPG","targetRectangle":{"y":1809.7257334434064,"x":1094.7022692405255,"width":354.93750000290834,"height":354.96006012108887}},{"text":"cropped-vishnu-boddeti.jpg","targetRectangle":{"y":1802.663959485413,"x":2515.6683546723139,"width":354.98117001640685,"height":354.96630795585975}},{"text":"neurips_logo.pdf","targetRectangle":{"y":73.205703735351562,"x":3130.176513671875,"width":652.657958984375,"height":293.69607543945312}},{"text":"Michigan_State_University_seal.svg.png","targetRectangle":{"y":62.693801879882812,"x":155.93951416015625,"width":387.13482666015625,"height":387.33645629882812}}],"baseLayer":{"animations":[],"initialState":{"affineTransform":[1,0,0,1,0,0],"masksToBounds":false,"rotation":0,"scale":1,"position":{"pointX":1944,"pointY":1296},"width":3888,"sublayerTransform":[1,0,0,0,0,1,0,0,0,0,1,0,0,0,0,1],"contentsRect":{"y":0,"x":0,"width":1,"height":1},"opacity":1,"edgeAntialiasingMask":251658240,"height":2592,"hidden":false,"anchorPoint":{"pointX":0.5,"pointY":0.5}},"objectID":"0","layers":[{"animations":[],"initialState":{"affineTransform":[1,0,0,1,0,0],"masksToBounds":false,"rotation":0,"scale":1,"position":{"pointX":1944,"pointY":1296},"width":3888,"sublayerTransform":[1,0,0,0,0,1,0,0,0,0,1,-0.00014586630194489994,0,0,0,1],"contentsRect":{"y":0,"x":0,"width":1,"height":1},"opacity":1,"edgeAntialiasingMask":251658240,"height":2592,"hidden":false,"anchorPoint":{"pointX":0.5,"pointY":0.5}},"layers":[{"animations":[],"layers":[],"texturedRectangle":{"isBackgroundTexture":false,"singleTextureOpacity":1,"textureType":0,"textBaseline":0,"textXHeight":0,"isVerticalText":false},"initialState":{"affineTransform":[1,0,0,1,0,0],"masksToBounds":false,"rotation":0,"scale":1,"position":{"pointX":1944,"pointY":1296},"width":3888,"sublayerTransform":[1,0,0,0,0,1,0,0,0,0,1,0,0,0,0,1],"contentsRect":{"y":0,"x":0,"width":1,"height":1},"opacity":1,"edgeAntialiasingMask":0,"height":2592,"hidden":false,"anchorPoint":{"pointX":0.5,"pointY":0.5}},"texture":"45E1395873AAC4F7B3CE3849968C4655"}]}]}}]}